dju_privateurl/__init__.py
dju_privateurl/admin.py
dju_privateurl/apps.py
dju_privateurl/models.py
dju_privateurl/signals.py
dju_privateurl/urls.py
dju_privateurl/views.py
dju_privateurl/locale/en/LC_MESSAGES/django.mo
dju_privateurl/locale/en/LC_MESSAGES/django.po
dju_privateurl/locale/ru/LC_MESSAGES/django.mo
dju_privateurl/locale/ru/LC_MESSAGES/django.po
dju_privateurl/locale/uk/LC_MESSAGES/django.mo
dju_privateurl/locale/uk/LC_MESSAGES/django.po
dju_privateurl/migrations/0001_initial.py
dju_privateurl/migrations/0002_auto_20160501_0153.py
dju_privateurl/migrations/__init__.py
dju_privateurl-0.0.9.dist-info/DESCRIPTION.rst
dju_privateurl-0.0.9.dist-info/METADATA
dju_privateurl-0.0.9.dist-info/RECORD
dju_privateurl-0.0.9.dist-info/WHEEL
dju_privateurl-0.0.9.dist-info/metadata.json
dju_privateurl-0.0.9.dist-info/top_level.txt
