Metadata-Version: 2.0
Name: dju-privateurl
Version: 0.0.9
Summary: Django Utils: Private URL
Home-page: https://github.com/liminspace/dju-privateurl
Author: Igor Melnyk
Author-email: liminspace@gmail.com
License: MIT
Platform: UNKNOWN
Requires-Dist: django (>=1.9.<1.11)
Requires-Dist: dju-common
